build.py
publish.py
uvxship-0.1.1.dist-info/METADATA
uvxship-0.1.1.dist-info/WHEEL
uvxship-0.1.1.dist-info/entry_points.txt
uvxship-0.1.1.dist-info/top_level.txt
uvxship-0.1.1.dist-info/RECORD
