Metadata-Version: 2.4
Name: uvxship
Version: 0.1.1
Summary: Publish to PYPI with uv by a single command: `uvx ship` (fixes `uv build && uv ship`).
Author-email: Gwang-Jin Kim <gwang.jin.kim.phd@mgail.com>
License: MIT
Keywords: uv,uvx,publish,build,pypirc
Classifier: Programming Language :: Python :: 3
Classifier: License :: OSI Approved :: MIT License
Classifier: Operating System :: OS Independent
Requires-Python: >=3.8
